sample_packageee/__init__.py
sample_packageee/sample.py
sample_packageee-0.2.0.dist-info/WHEEL
sample_packageee-0.2.0.dist-info/METADATA
sample_packageee-0.2.0.dist-info/RECORD
